{
  "speakers": [
    {
      "id": "speaker_1",
      "label": "speaker_1"
    },
    {
      "id": "speaker_2",
      "label": "speaker_2"
    }
  ],
  "role_map": {
    "manager": "unknown",
    "client": "unknown"
  },
  "stats_sec": {
    "speaker_1": 0.0,
    "speaker_2": 0.0
  },
  "turns": [
    {
      "speaker": "speaker_1",
      "start": 0.0,
      "end": 0.0,
      "text": "Мы тут для того, чтобы создать кое-что великое, а не для того, чтобы тухнуть."
    },
    {
      "speaker": "speaker_1",
      "start": 0.0,
      "end": 0.0,
      "text": "Поэтому ты тоже держи вот этот ориентир постоянного роста, постоянного достижения чего-то нового."
    },
    {
      "speaker": "speaker_1",
      "start": 0.0,
      "end": 0.0,
      "text": "Что-то вышло, ты видишь, вот ты как инженер видишь, что, блин, ребят, там кто-то уже сделал огромную работу, и сейчас за небольшие деньги можно купить весь его опыт, весь его путь и взять уже продукт и использовать это."
    },
    {
      "speaker": "speaker_1",
      "start": 0.0,
      "end": 0.0,
      "text": "Взять уже готовую какую-то часть, но на которую у него ушли, может быть, месяцы, может быть, годы."
    },
    {
      "speaker": "speaker_1",
      "start": 0.0,
      "end": 0.0,
      "text": "И на самом деле, скорее всего, десятки тысяч долларов на разработку любого приложения, обычно это даже больше."
    },
    {
      "speaker": "speaker_1",
      "start": 0.0,
      "end": 0.0,
      "text": "Соответственно, если ты видишь, что хочется то проверить, это проверить под наши задачи, проэкспериментировать, то ты говори, мы в это будем вкладываться."
    },
    {
      "speaker": "speaker_1",
      "start": 0.0,
      "end": 0.0,
      "text": "И пусть это и у тебя одержит интерес, что у нас нет задачи как-то ужаться и как-то все бесплатно, влезть в какие-то щели маленькие, как-то пролезть и как-то исхитриться."
    },
    {
      "speaker": "speaker_1",
      "start": 0.0,
      "end": 0.0,
      "text": "Мы строим большую штуку, и у тебя есть вот эта свобода."
    },
    {
      "speaker": "speaker_1",
      "start": 0.0,
      "end": 0.0,
      "text": "Я к тебе прислушиваюсь и буду прислушиваться, поэтому если что-то для экспериментов тебе нужно, то ты говори."
    }
  ]
}